rtspware/__init__.py
rtspware/__main__.py
rtspware/saver.py
rtspware/subprocessutils.py
rtspware/writer.py
rtspware-0.1.1.dist-info/METADATA
rtspware-0.1.1.dist-info/WHEEL
rtspware-0.1.1.dist-info/entry_points.txt
rtspware-0.1.1.dist-info/RECORD
