Metadata-Version: 2.1
Name: rtspware
Version: 0.1.1
Summary: Tools for working with RTSP stream.
Author: ryzhovalex
Author-email: thed4rkof@gmail.com
Requires-Python: >=3.11,<4.0
Classifier: Programming Language :: Python :: 3
Classifier: Programming Language :: Python :: 3.11
Requires-Dist: opencv-python (>=4.8.0.76,<5.0.0.0)
Requires-Dist: pydantic (>=2.3.0,<3.0.0)
